vl_public_aws_ssm/__init__.py
vl_public_aws_ssm-0.1.1.dist-info/METADATA
vl_public_aws_ssm-0.1.1.dist-info/WHEEL
vl_public_aws_ssm-0.1.1.dist-info/top_level.txt
vl_public_aws_ssm-0.1.1.dist-info/RECORD
