Metadata-Version: 2.1
Name: vl-public-aws-ssm
Version: 0.1.1
Summary: Wrapper for reading cfg from aws ssm
Home-page: UNKNOWN
Author: UNKNOWN
Author-email: UNKNOWN
License: MIT
Platform: UNKNOWN
